ims_logger/__init__.py
ims_logger/ims_logger.py
ims_logger-0.1.0.dist-info/METADATA
ims_logger-0.1.0.dist-info/WHEEL
ims_logger-0.1.0.dist-info/top_level.txt
ims_logger-0.1.0.dist-info/RECORD
