Metadata-Version: 2.1
Name: ims_logger
Version: 0.1.0
Summary: Library created for logging in IMS application
Author: Allen
